qnc_data_tables/__init__.py
qnc_data_tables/_core.py
qnc_data_tables/py.typed
qnc_data_tables-0.0.2.dist-info/METADATA
qnc_data_tables-0.0.2.dist-info/WHEEL
qnc_data_tables-0.0.2.dist-info/top_level.txt
qnc_data_tables-0.0.2.dist-info/RECORD
