Metadata-Version: 2.4
Name: qnc_data_tables
Version: 0.0.2
Summary: Work-in-progress
Requires-Python: >=3.11
Requires-Dist: django<6,>=4.2.19
Requires-Dist: html_generators<3,>=2.8.0
